README.md
setup.cfg
setup.py
test/test_balance.py
test/test_balance_delta.py
test/test_check_result.py
test/test_inline_response400.py
test/test_inline_response401.py
test/test_inline_response415.py
test/test_inline_response429.py
test/test_inline_response500.py
test/test_inline_response501.py
test/test_inline_response502.py
test/test_inline_response503.py
test/test_inline_response504.py
test/test_inline_response_default.py
test/test_plan_api.py
test/test_plan_result.py
test/test_plan_task.py
test/test_storage.py
test/test_storage_tariff.py
test/test_system_api.py
test/test_trace_data.py
test/test_transfer.py
test/test_validate_api.py
test/test_validate_result.py
test/test_validation.py
test/test_version_result.py
vrt_lss_stock/__init__.py
vrt_lss_stock/api_client.py
vrt_lss_stock/configuration.py
vrt_lss_stock/exceptions.py
vrt_lss_stock/rest.py
vrt_lss_stock.egg-info/PKG-INFO
vrt_lss_stock.egg-info/SOURCES.txt
vrt_lss_stock.egg-info/dependency_links.txt
vrt_lss_stock.egg-info/requires.txt
vrt_lss_stock.egg-info/top_level.txt
vrt_lss_stock/api/__init__.py
vrt_lss_stock/api/plan_api.py
vrt_lss_stock/api/system_api.py
vrt_lss_stock/api/validate_api.py
vrt_lss_stock/models/__init__.py
vrt_lss_stock/models/balance.py
vrt_lss_stock/models/balance_delta.py
vrt_lss_stock/models/check_result.py
vrt_lss_stock/models/inline_response400.py
vrt_lss_stock/models/inline_response401.py
vrt_lss_stock/models/inline_response415.py
vrt_lss_stock/models/inline_response429.py
vrt_lss_stock/models/inline_response500.py
vrt_lss_stock/models/inline_response501.py
vrt_lss_stock/models/inline_response502.py
vrt_lss_stock/models/inline_response503.py
vrt_lss_stock/models/inline_response504.py
vrt_lss_stock/models/inline_response_default.py
vrt_lss_stock/models/plan_result.py
vrt_lss_stock/models/plan_task.py
vrt_lss_stock/models/storage.py
vrt_lss_stock/models/storage_tariff.py
vrt_lss_stock/models/trace_data.py
vrt_lss_stock/models/transfer.py
vrt_lss_stock/models/validate_result.py
vrt_lss_stock/models/validation.py
vrt_lss_stock/models/version_result.py
vrt_lss_stock/schemes/__init__.py
vrt_lss_stock/schemes/plan_result_schema.py
