Metadata-Version: 1.0
Name: vrt-lss-stock
Version: 3.9.172873
Summary: Veeroute.Stock
Home-page: https://docs.veeroute.com/#/lss/stock
Author: Veeroute Support Team
Author-email: support@veeroute.com
License: UNKNOWN
Keywords: OpenAPI,OpenAPI-Generator,Veeroute.Stock
Platform: UNKNOWN
